artemis/__init__.py
artemis/exceptions.py
artemis/analytics/__init__.py
artemis/analytics/metrics.py
artemis/analytics/momentum.py
artemis/analytics/types.py
artemis/analytics/visualizations.py
artemis/core/__init__.py
artemis/core/agent.py
artemis/core/aggregation.py
artemis/core/argument.py
artemis/core/causal.py
artemis/core/causal_analysis.py
artemis/core/causal_strategy.py
artemis/core/causal_visualization.py
artemis/core/debate.py
artemis/core/decomposition.py
artemis/core/disagreement.py
artemis/core/ethics.py
artemis/core/evaluation.py
artemis/core/evidence.py
artemis/core/feedback.py
artemis/core/hierarchical.py
artemis/core/jury.py
artemis/core/llm_evaluation.py
artemis/core/llm_extraction.py
artemis/core/multimodal_evidence.py
artemis/core/streaming.py
artemis/core/types.py
artemis/core/prompts/__init__.py
artemis/core/prompts/hdag.py
artemis/core/prompts/jury.py
artemis/core/verification/__init__.py
artemis/core/verification/citation_validator.py
artemis/core/verification/rules.py
artemis/core/verification/verifier.py
artemis/integrations/__init__.py
artemis/integrations/crewai.py
artemis/integrations/langchain.py
artemis/integrations/langgraph.py
artemis/mcp/__init__.py
artemis/mcp/cli.py
artemis/mcp/server.py
artemis/mcp/sessions.py
artemis/mcp/tools.py
artemis/models/__init__.py
artemis/models/adapters.py
artemis/models/anthropic.py
artemis/models/base.py
artemis/models/deepseek.py
artemis/models/google.py
artemis/models/openai.py
artemis/models/reasoning.py
artemis/prompts/__init__.py
artemis/prompts/loader.py
artemis/prompts/v1/__init__.py
artemis/prompts/v1/benchmark.py
artemis/prompts/v1/evaluation.py
artemis/prompts/v1/extraction.py
artemis/prompts/v1/hdag.py
artemis/prompts/v1/jury.py
artemis/safety/__init__.py
artemis/safety/base.py
artemis/safety/behavior.py
artemis/safety/deception.py
artemis/safety/ethics_guard.py
artemis/safety/sandbagging.py
artemis/steering/__init__.py
artemis/steering/analyzer.py
artemis/steering/controller.py
artemis_agents-2.0.0.dist-info/METADATA
artemis_agents-2.0.0.dist-info/WHEEL
artemis_agents-2.0.0.dist-info/entry_points.txt
artemis_agents-2.0.0.dist-info/licenses/LICENSE
artemis_agents-2.0.0.dist-info/RECORD
