Metadata-Version: 2.4
Name: artemis-agents
Version: 2.0.0
Summary: Production-ready multi-agent debate framework with adaptive evaluation and safety monitoring
Project-URL: Homepage, https://github.com/bassrehab/artemis-agents
Project-URL: Documentation, https://artemis.subhadipmitra.com
Project-URL: Repository, https://github.com/bassrehab/artemis-agents.git
Project-URL: Issues, https://github.com/bassrehab/artemis-agents/issues
Project-URL: Changelog, https://github.com/bassrehab/artemis-agents/blob/main/CHANGELOG.md
Author-email: Subhadip Mitra <contact@subhadipmitra.com>
License: Apache-2.0
License-File: LICENSE
Keywords: agents,ai,ai-safety,debate,decision-making,langchain,langgraph,llm,multi-agent
Classifier: Development Status :: 4 - Beta
Classifier: Intended Audience :: Developers
Classifier: Intended Audience :: Science/Research
Classifier: License :: OSI Approved :: Apache Software License
Classifier: Operating System :: OS Independent
Classifier: Programming Language :: Python :: 3
Classifier: Programming Language :: Python :: 3.10
Classifier: Programming Language :: Python :: 3.11
Classifier: Programming Language :: Python :: 3.12
Classifier: Topic :: Scientific/Engineering :: Artificial Intelligence
Classifier: Typing :: Typed
Requires-Python: >=3.10
Requires-Dist: anthropic>=0.20
Requires-Dist: google-generativeai>=0.3.0
Requires-Dist: httpx>=0.25.0
Requires-Dist: openai>=1.0
Requires-Dist: pydantic>=2.0
Requires-Dist: structlog>=23.0
Requires-Dist: tenacity>=8.0
Provides-Extra: all
Requires-Dist: crewai>=0.1.0; extra == 'all'
Requires-Dist: fastmcp>=0.1.0; extra == 'all'
Requires-Dist: langchain-core>=0.1.0; extra == 'all'
Requires-Dist: langgraph>=0.0.20; extra == 'all'
Provides-Extra: crewai
Requires-Dist: crewai>=0.1.0; extra == 'crewai'
Provides-Extra: dev
Requires-Dist: ipython>=8.0; extra == 'dev'
Requires-Dist: mypy>=1.5; extra == 'dev'
Requires-Dist: pre-commit>=3.0; extra == 'dev'
Requires-Dist: pytest-asyncio>=0.21; extra == 'dev'
Requires-Dist: pytest-cov>=4.0; extra == 'dev'
Requires-Dist: pytest>=7.0; extra == 'dev'
Requires-Dist: ruff>=0.1.0; extra == 'dev'
Provides-Extra: langchain
Requires-Dist: langchain-core>=0.1.0; extra == 'langchain'
Provides-Extra: langgraph
Requires-Dist: langgraph>=0.0.20; extra == 'langgraph'
Provides-Extra: mcp
Requires-Dist: fastmcp>=0.1.0; extra == 'mcp'
